Workbook

Sheet FERRAMENTA
A10: CONFIGURAÇÕES
A11: Salário | B11: 5000
A12: Rendimento da carteira | B12: 0.01
A13: Sugestões de investimento (40%) | B13: =B11*40% -> 2000
A15: INVESTIMENTO MENSAL
A16: Quanto investir mensalmente? | B16: 2000
A17: Por quantos anos? | B17: 5
A18: Taxa mensal? | B18: 0.01
A19: Patrimônio final? | B19: =FV(B18, B17*12, -B16) -> 163339.34
A20: Dividendos mensais? | B20: =B19*$B$12 -> 1633.3934
A22: CENÁRIOS | C22: DIVIDENDOS
A23: Quanto em 2 anos? | B23: =FV($B$18, 2*12, -$B$16) -> 53946.93 | C23: =FV($B$18, 2*12, -$B$16)*B12 -> 539.4693
A24: Quanto em 5 anos? | B24: =FV($B$18, 5*12, -$B$16) -> 163339.34 | C24: =FV($B$18, 5*12, -$B$16)*B12 -> 1633.3934
A25: Quanto em 10 anos? | B25: =FV($B$18, 10*12, -$B$16) -> 460077.38 | C25: =FV($B$18, 10*12, -$B$16)*B12 -> 4600.7738
A26: Quanto em 20 anos? | B26: =FV($B$18, 20*12, -$B$16) -> 1978510.7 | C26: =FV($B$18, 20*12, -$B$16)*B12 -> 19785.107
A27: Quanto em 30 anos? | B27: =FV($B$18, 30*12, -$B$16) -> 6989928.3 | C27: =FV($B$18, 30*12, -$B$16)*B12 -> 69899.283
A29: PERFIL | B29: AGRESSIVO
A30: VALOR A INVESTIR POR MÊS | B30: =B16 -> 2000
A32: TIPO DE FII | B32: PERCENTUAL SUGERIDO | C32: VALORES
A33: PAPEL | B33: =VLOOKUP($B$29&"-"&A33, com!$A:$D, 4, FALSE) -> 0.2 | C33: =B33*$B$16 -> 400
A34: TIJOLO | B34: =VLOOKUP($B$29&"-"&A34, com!$A:$D, 4, FALSE) -> 0.25 | C34: =B34*$B$16 -> 500
A35: HÍBRIDOS | B35: =VLOOKUP($B$29&"-"&A35, com!$A:$D, 4, FALSE) -> 0.1 | C35: =B35*$B$16 -> 200
A36: FOFs | B36: =VLOOKUP($B$29&"-"&A36, com!$A:$D, 4, FALSE) -> 0.1 | C36: =B36*$B$16 -> 200
A37: DESENVOLVIMENTO | B37: =VLOOKUP($B$29&"-"&A37, com!$A:$D, 4, FALSE) -> 0.2 | C37: =B37*$B$16 -> 400
A38: HOTELARIAS | B38: =VLOOKUP($B$29&"-"&A38, com!$A:$D, 4, FALSE) -> 0.15 | C38: =B38*$B$16 -> 300
C39: =SUM(C33:C38) -> 2000

Sheet com
A1: CHAVE | B1: PERFIL | C1: TIPO DE FII | D1: %
A2: =B2&"-"&C2 -> CONSERVADOR-PAPEL | B2: CONSERVADOR | C2: PAPEL | D2: 0.5
A3: =B3&"-"&C3 -> CONSERVADOR-TIJOLO | B3: CONSERVADOR | C3: TIJOLO | D3: 0.3 | G3: =$B$9&"-"&$C$9 -> MODERADO-TIJOLO | H3: =VLOOKUP(G3, $A:$D, 4, FALSE) -> 0.3
A4: =B4&"-"&C4 -> CONSERVADOR-HÍBRIDOS | B4: CONSERVADOR | C4: HÍBRIDOS | D4: 0.1
A5: =B5&"-"&C5 -> CONSERVADOR-FOFs | B5: CONSERVADOR | C5: FOFs | D5: 0.1
A6: =B6&"-"&C6 -> CONSERVADOR-DESENVOLVIMENTO | B6: CONSERVADOR | C6: DESENVOLVIMENTO | D6: 0
A7: =B7&"-"&C7 -> CONSERVADOR-HOTELARIAS | B7: CONSERVADOR | C7: HOTELARIAS | D7: 0
A8: =B8&"-"&C8 -> MODERADO-PAPEL | B8: MODERADO | C8: PAPEL | D8: 0.3
A9: =$B$9&"-"&$C$9 -> MODERADO-TIJOLO | B9: MODERADO | C9: TIJOLO | D9: 0.3
A10: =B10&"-"&C10 -> MODERADO-HÍBRIDOS | B10: MODERADO | C10: HÍBRIDOS | D10: 0.15
A11: =B11&"-"&C11 -> MODERADO-FOFs | B11: MODERADO | C11: FOFs | D11: 0.1
A12: =B12&"-"&C12 -> MODERADO-DESENVOLVIMENTO | B12: MODERADO | C12: DESENVOLVIMENTO | D12: 0.1
A13: =B13&"-"&C13 -> MODERADO-HOTELARIAS | B13: MODERADO | C13: HOTELARIAS | D13: 0.05
A14: =B14&"-"&C14 -> AGRESSIVO-PAPEL | B14: AGRESSIVO | C14: PAPEL | D14: 0.2
A15: =B15&"-"&C15 -> AGRESSIVO-TIJOLO | B15: AGRESSIVO | C15: TIJOLO | D15: 0.25
A16: =B16&"-"&C16 -> AGRESSIVO-HÍBRIDOS | B16: AGRESSIVO | C16: HÍBRIDOS | D16: 0.1
A17: =B17&"-"&C17 -> AGRESSIVO-FOFs | B17: AGRESSIVO | C17: FOFs | D17: 0.1
A18: =B18&"-"&C18 -> AGRESSIVO-DESENVOLVIMENTO | B18: AGRESSIVO | C18: DESENVOLVIMENTO | D18: 0.2
A19: =B19&"-"&C19 -> AGRESSIVO-HOTELARIAS | B19: AGRESSIVO | C19: HOTELARIAS | D19: 0.15
